[
  {
    "id": "spring-kickoff-2025",
    "title": "Spring 2025 Kickoff Meeting",
    "date": "2025-01-15",
    "time": "6:00 PM - 8:00 PM",
    "location": "ENG 103, Toronto Metropolitan University",
    "category": "Social",
    "description": "Join us for our spring semester kickoff! Meet the team, learn about upcoming events, and connect with fellow aerospace enthusiasts.",
    "speakers": [],
    "rsvpLink": "https://forms.gle/example1",
    "tags": ["networking", "welcome", "spring"],
    "image": null,
    "featured": true,
    "status": "upcoming"
  },
  {
    "id": "boeing-industry-talk",
    "title": "Industry Talk: Boeing Canada",
    "date": "2025-01-28",
    "time": "5:30 PM - 7:00 PM",
    "location": "Virtual (Zoom)",
    "category": "Talk",
    "description": "Hear from Boeing Canada engineers about career paths in aerospace, current projects, and what it takes to succeed in the industry.",
    "speakers": ["Sarah Chen, Senior Aerospace Engineer", "Michael Torres, Systems Integration Lead"],
    "rsvpLink": "https://forms.gle/example2",
    "tags": ["industry", "career", "boeing"],
    "image": null,
    "featured": true,
    "status": "upcoming"
  },
  {
    "id": "cad-workshop-solidworks",
    "title": "SolidWorks CAD Workshop",
    "date": "2025-02-08",
    "time": "2:00 PM - 5:00 PM",
    "location": "ENG 204, Computer Lab",
    "category": "Workshop",
    "description": "Hands-on workshop covering aerospace component design in SolidWorks. Perfect for beginners and intermediate users looking to improve their CAD skills.",
    "speakers": ["Alex Kim, Technical Lead"],
    "rsvpLink": "https://forms.gle/example3",
    "tags": ["technical", "CAD", "hands-on"],
    "image": null,
    "featured": true,
    "status": "upcoming"
  },
  {
    "id": "mda-facility-tour",
    "title": "MDA Space Facility Tour",
    "date": "2025-02-22",
    "time": "10:00 AM - 2:00 PM",
    "location": "MDA Space, Brampton",
    "category": "Tour",
    "description": "Exclusive tour of MDA Space facilities. See Canadarm technology up close and learn about Canada's contributions to space exploration.",
    "speakers": [],
    "rsvpLink": "https://forms.gle/example4",
    "tags": ["tour", "space", "MDA"],
    "image": null,
    "featured": false,
    "status": "upcoming"
  },
  {
    "id": "fall-networking-mixer",
    "title": "Fall 2024 Networking Mixer",
    "date": "2024-11-20",
    "time": "6:00 PM - 9:00 PM",
    "location": "The Oakham House",
    "category": "Social",
    "description": "End-of-semester celebration with industry professionals, alumni, and current members. Great food, great conversations.",
    "speakers": [],
    "rsvpLink": null,
    "tags": ["networking", "social", "alumni"],
    "image": null,
    "featured": false,
    "status": "past"
  },
  {
    "id": "rocket-propulsion-basics",
    "title": "Workshop: Rocket Propulsion Basics",
    "date": "2024-10-15",
    "time": "4:00 PM - 6:00 PM",
    "location": "ENG 103",
    "category": "Workshop",
    "description": "Introduction to rocket propulsion fundamentals. Covered liquid vs solid propellants, thrust equations, and design considerations.",
    "speakers": ["Dr. James Wright, Faculty Advisor"],
    "rsvpLink": null,
    "tags": ["technical", "propulsion", "workshop"],
    "image": null,
    "featured": false,
    "status": "past"
  }
]
